naive_translator/__init__.py
naive_translator/__main__.py
naive_translator/config.py
naive_translator/dictionary.py
naive_translator/server.py
naive_translator/translator.py
naive_translator/utils.py
naive_translator/data/dictionary
naive_translator/data/logs/.gitkeep
naive_translator-0.0.1.dist-info/LICENSE
naive_translator-0.0.1.dist-info/METADATA
naive_translator-0.0.1.dist-info/WHEEL
naive_translator-0.0.1.dist-info/entry_points.txt
naive_translator-0.0.1.dist-info/top_level.txt
naive_translator-0.0.1.dist-info/RECORD
