Metadata-Version: 2.1
Name: naive-translator
Version: 0.0.1
Summary: A naive word by word translator
Home-page: https://github.com/ZhenningLang/naive_translator
Author: langzhenning
Author-email: zhenninglang@163.com
License: UNKNOWN
Platform: UNKNOWN
Classifier: Programming Language :: Python :: 3
Classifier: License :: OSI Approved :: MIT License
Classifier: Operating System :: OS Independent
Requires-Python: >=3.2
Requires-Dist: tornado
